setup.py
uio.py
pycopy_cpython_uio.egg-info/PKG-INFO
pycopy_cpython_uio.egg-info/SOURCES.txt
pycopy_cpython_uio.egg-info/dependency_links.txt
pycopy_cpython_uio.egg-info/top_level.txt